{"assets/images/creation_background.jpg":["assets/images/creation_background.jpg"],"assets/images/cuteRaccoon.bmp":["assets/images/cuteRaccoon.bmp"],"assets/images/empty_background.jpg":["assets/images/empty_background.jpg"],"assets/images/game_sheet.png":["assets/images/game_sheet.png"],"assets/images/game_sheet_easy.png":["assets/images/game_sheet_easy.png"],"assets/images/game_sheet_hard.png":["assets/images/game_sheet_hard.png"],"assets/images/hallelujaRaccoon.jpeg":["assets/images/hallelujaRaccoon.jpeg"],"assets/images/menu_background.jpg":["assets/images/menu_background.jpg"],"assets/images/selection_background.jpg":["assets/images/selection_background.jpg"],"assets/images/shookRaccoon.bmp":["assets/images/shookRaccoon.bmp"],"assets/images/sleepyRaccoon.jpg":["assets/images/sleepyRaccoon.jpg"]}